mcpstack_mimic-0.0.1.dist-info/METADATA
mcpstack_mimic-0.0.1.dist-info/WHEEL
mcpstack_mimic-0.0.1.dist-info/entry_points.txt
mcpstack_mimic-0.0.1.dist-info/licenses/LICENSE
mcpstack_mimic/__init__.py
mcpstack_mimic/tools/mimic/__init__.py
mcpstack_mimic/tools/mimic/backend/backends/bigquery.py
mcpstack_mimic/tools/mimic/backend/backends/sqlite.py
mcpstack_mimic/tools/mimic/backend/base.py
mcpstack_mimic/tools/mimic/backend/registry.py
mcpstack_mimic/tools/mimic/cli.py
mcpstack_mimic/tools/mimic/components/__init__.py
mcpstack_mimic/tools/mimic/components/auth.py
mcpstack_mimic/tools/mimic/components/data_io.py
mcpstack_mimic/tools/mimic/components/utils.py
mcpstack_mimic/tools/mimic/configurations/datasets.yaml
mcpstack_mimic/tools/mimic/configurations/env_vars.yaml
mcpstack_mimic/tools/mimic/configurations/security.yaml
mcpstack_mimic/tools/mimic/mimic.py
mcpstack_mimic-0.0.1.dist-info/RECORD
