Metadata-Version: 2.4
Name: mcpstack-mimic
Version: 0.0.1
Summary: MIMIC-IV MCPStack tool (standalone package) with pluggable SQLite/BigQuery backends.
Keywords: mcp,mcpstack,mimic-iv,tool,healthcare,bigquery,sqlite
Author-Email: Provost Simon <s.g.provost@kent.ac.uk>
License-Expression: MIT
Requires-Python: >=3.10
Requires-Dist: typer>=0.9.0
Requires-Dist: rich>=13.0.0
Requires-Dist: requests>=2.30.0
Requires-Dist: beautifulsoup4>=4.12.0
Requires-Dist: polars[pyarrow]>=0.20.10
Requires-Dist: appdirs>=1.4.0
Requires-Dist: sqlalchemy>=2.0.0
Requires-Dist: pandas>=2.0.0
Requires-Dist: fastmcp>=0.1.0
Requires-Dist: google-cloud-bigquery>=3.0.0
Requires-Dist: db-dtypes>=1.0.0
Requires-Dist: sqlparse>=0.4.0
Requires-Dist: pyjwt[crypto]>=2.8.0
Requires-Dist: cryptography>=41.0.0
Requires-Dist: python-jose[cryptography]>=3.3.0
Requires-Dist: httpx>=0.24.0
Requires-Dist: pyaml>=25.7.0
Requires-Dist: beartype>=0.21.0
Requires-Dist: thefuzz>=0.22.1
Requires-Dist: rich-pyfiglet>=0.1.4
Requires-Dist: click==8.1.8
Requires-Dist: mcpstack>=0.0.2
Requires-Dist: pytest==7.4.3
Requires-Dist: pytest-asyncio>=0.23.8
